variable_protocols/__init__.py
variable_protocols/base_variables.py
variable_protocols/common_variables.py
variable_protocols/hashed_tree.py
variable_protocols/protocols.py
variable_protocols/py.typed
variable_protocols/transformations.py
variable_protocols/utils.py
variable_protocols/variables.py
variable_protocols-1.3.2.dist-info/LICENSE
variable_protocols-1.3.2.dist-info/METADATA
variable_protocols-1.3.2.dist-info/WHEEL
variable_protocols-1.3.2.dist-info/top_level.txt
variable_protocols-1.3.2.dist-info/RECORD
