Metadata-Version: 2.1
Name: variable_protocols
Version: 1.3.2
Summary: A protocol for machine learning variables
Home-page: https://github.com/cwhy/variable_protocols
Author: cwhy
Author-email: chenyu.nus@gmail.com
License: GPL v3
Platform: UNKNOWN
Requires-Python: >=3.7
License-File: LICENSE
